Workbook

Sheet Synthèse
A1: BUDGET PLURIANNUEL DU FONDS DE DOTATION
A2: Trois exercices pleins — 2027, 2028 et 2029 — précédés de l'exercice de constitution 2026.
A5: Poste | B5: 2026 | C5: 2027 | D5: 2028 | E5: 2029 | F5: Total 3 ans 2027-2029 | G5: Total période 2026-2029
A6: RESSOURCES
A7: Ressources mobilisables — total | B7: =Ressources!B27 -> 157527.72 | C7: =Ressources!C27 -> 1568060.7 | D7: =Ressources!D27 -> 2217400 | E7: =Ressources!E27 -> 900 | F7: =SUM(C7:E7) -> 3786360.7 | G7: =SUM(B7:E7) -> 3943888.4
A8: dont mécénat d'entreprise — trois levées | B8: =Ressources!B12+Ressources!B13+Ressources!B14 -> 157452.72 | C8: =Ressources!C12+Ressources!C13+Ressources!C14 -> 1567535.7 | D8: =Ressources!D12+Ressources!D13+Ressources!D14 -> 2216500 | E8: =Ressources!E12+Ressources!E13+Ressources!E14 -> 0 | F8: =SUM(C8:E8) -> 3784035.7 | G8: =SUM(B8:E8) -> 3941488.4
A9: dont revenus de la dotation | B9: =Ressources!B11 -> 75 | C9: =Ressources!C11 -> 525 | D9: =Ressources!D11 -> 900 | E9: =Ressources!E11 -> 900 | F9: =SUM(C9:E9) -> 2325 | G9: =SUM(B9:E9) -> 2400
A10: TOTAL DES RESSOURCES MOBILISABLES | B10: =B7 -> 157527.72 | C10: =C7 -> 1568060.7 | D10: =D7 -> 2217400 | E10: =E7 -> 900 | F10: =SUM(C10:E10) -> 3786360.7 | G10: =SUM(B10:E10) -> 3943888.4
A12: EMPLOIS
A13: P1 — CONNAÎTRE ET SUIVRE LES MILIEUX MARINS | B13: =A_P1!B28 -> 0 | C13: =A_P1!C28 -> 150000 | D13: =A_P1!D28 -> 150000 | E13: =A_P1!E28 -> 150000 | F13: =SUM(C13:E13) -> 450000 | G13: =SUM(B13:E13) -> 450000
A14: P2 — RESTAURATION DES ÉCOSYSTÈMES | B14: =A_P2!B28 -> 0 | C14: =A_P2!C28 -> 800000 | D14: =A_P2!D28 -> 0 | E14: =A_P2!E28 -> 0 | F14: =SUM(C14:E14) -> 800000 | G14: =SUM(B14:E14) -> 800000
A15: P3 — DÉPOLLUTION DES MILIEUX | B15: =A_P3!B28 -> 43000 | C15: =A_P3!C28 -> 43000 | D15: =A_P3!D28 -> 43000 | E15: =A_P3!E28 -> 43000 | F15: =SUM(C15:E15) -> 129000 | G15: =SUM(B15:E15) -> 172000
A16: P4 — MODERNISATION DE LA FILIÈRE PÊCHE | B16: =A_P4!B28 -> 70000 | C16: =A_P4!C28 -> 108350 | D16: =A_P4!D28 -> 2048350 | E16: =A_P4!E28 -> 67850 | F16: =SUM(C16:E16) -> 2224550 | G16: =SUM(B16:E16) -> 2294550
A17: A — Enveloppes de programme | B17: =SUM(B13:B16) -> 113000 | C17: =SUM(C13:C16) -> 1101350 | D17: =SUM(D13:D16) -> 2241350 | E17: =SUM(E13:E16) -> 260850 | F17: =SUM(C17:E17) -> 3603550 | G17: =SUM(B17:E17) -> 3716550
A18: B — Moyens communs | B18: ='B · Moyens communs'!B10 -> 2120 | C18: ='B · Moyens communs'!C10 -> 9707.23 | D18: ='B · Moyens communs'!D10 -> 25663.52 | E18: ='B · Moyens communs'!E10 -> 35216.28 | F18: =SUM(C18:E18) -> 70587.03 | G18: =SUM(B18:E18) -> 72707.03
A19: C — Frais de fonctionnement | B19: ='C · Fonctionnement'!B17 -> 300 | C19: ='C · Fonctionnement'!C17 -> 32325.49 | D19: ='C · Fonctionnement'!D17 -> 59875.72 | E19: ='C · Fonctionnement'!E17 -> 62130.17 | F19: =SUM(C19:E19) -> 154331.38 | G19: =SUM(B19:E19) -> 154631.38
A20: TOTAL DES EMPLOIS (A + B + C) | B20: =B17+B18+B19 -> 115420 | C20: =C17+C18+C19 -> 1143382.7 | D20: =D17+D18+D19 -> 2326889.2 | E20: =E17+E18+E19 -> 358196.45 | F20: =SUM(C20:E20) -> 3828468.4 | G20: =SUM(B20:E20) -> 3943888.4
A22: ÉQUILIBRE
A23: Résultat de l'exercice | B23: =B10-B20 -> 42107.72 | C23: =C10-C20 -> 424677.97 | D23: =D10-D20 -> -109489.24 | E23: =E10-E20 -> -357296.45 | F23: =SUM(C23:E23) -> -42107.72 | G23: =SUM(B23:E23) -> 0
A24: Réserve non affectée, cumulée en fin d'exercice | B24: =B23 -> 42107.72 | C24: =B24+C23 -> 466785.69 | D24: =C24+D23 -> 357296.45 | E24: =D24+E23 -> 0
A25: Alerte | B25: =IF(B24<0,"NON COUVERT","ok") -> ok | C25: =IF(C24<0,"NON COUVERT","ok") -> ok | D25: =IF(D24<0,"NON COUVERT","ok") -> ok | E25: =IF(E24<0,"NON COUVERT","ok") -> ok
A27: DOTATION NON CONSOMPTIBLE — HORS BUDGET D'EMPLOIS
A28: Versements à la dotation | B28: =Ressources!B7 -> 15000 | C28: =Ressources!C7 -> 30000 | D28: =Ressources!D7 -> 0 | E28: =Ressources!E7 -> 0 | F28: =SUM(C28:E28) -> 30000 | G28: =SUM(B28:E28) -> 45000
A30: POUR MÉMOIRE — HORS BUDGET DU FONDS
A31: Subventions publiques portées par l'association (80 % de l'assiette éligible) | B31: 0 | C31: 29607.11 | D31: 55110.94 | E31: 55804.3 | F31: =SUM(C31:E31) -> 140522.35 | G31: =SUM(B31:E31) -> 140522.35
A32: Refacturations reçues par l'association (fonds : 0,20 ETP et moyens matériels ; Mare Services : 0,20 ETP) | B32: 0 | C32: 12550.98 | D32: 25527.44 | E32: 26008.34 | F32: =SUM(C32:E32) -> 64086.76 | G32: =SUM(B32:E32) -> 64086.76
A33: Montants reversés aux professionnels via Mare Services | B33: 0 | C33: 28480 | D33: 28480 | E33: 28480 | F33: =SUM(C33:E33) -> 85440 | G33: =SUM(B33:E33) -> 85440
A35: Les lignes de ressources et d'emplois sont des reports. Seules les trois lignes « pour mémoire » sont saisies ici.

Sheet Budget global
A1: BUDGET GLOBAL DU FONDS — VUE RESSOURCES / EMPLOIS
A2: Vue détaillée par canal de collecte. Reprend les onglets Ressources, A_P1 à A_P4, B et C.
A5: Poste | B5: 2026 | C5: 2027 | D5: 2028 | E5: 2029 | F5: Total 3 ans 2027-2029 | G5: Total période 2026-2029 | H5: Source / commentaire
A6: RESSOURCES
A7: Dotation initiale — capital non consomptible | B7: =Ressources!B7 -> 15000 | C7: =Ressources!C7 -> 30000 | D7: =Ressources!D7 -> 0 | E7: =Ressources!E7 -> 0 | F7: =SUM(C7:E7) -> 30000 | G7: =SUM(B7:E7) -> 45000 | H7: Non mobilisable : ne finance aucun emploi.
A8: Revenus de la dotation — produits de placement | B8: =Ressources!B11 -> 75 | C8: =Ressources!C11 -> 525 | D8: =Ressources!D11 -> 900 | E8: =Ressources!E11 -> 900 | F8: =SUM(C8:E8) -> 2325 | G8: =SUM(B8:E8) -> 2400 | H8: Rendement de 2 % sur le capital placé.
A9: Mécénat d'entreprise — levée 1 (amorçage) | B9: =Ressources!B12 -> 157452.72 | C9: =Ressources!C12 -> 0 | D9: =Ressources!D12 -> 0 | E9: =Ressources!E12 -> 0 | F9: =SUM(C9:E9) -> 0 | G9: =SUM(B9:E9) -> 157452.72 | H9: Encaissée au T4 2026.
A10: Mécénat d'entreprise — levée 2 (programmes) | B10: =Ressources!B13 -> 0 | C10: =Ressources!C13 -> 1567535.7 | D10: =Ressources!D13 -> 0 | E10: =Ressources!E13 -> 0 | F10: =SUM(C10:E10) -> 1567535.7 | G10: =SUM(B10:E10) -> 1567535.7 | H10: Encaissée au T1 2027.
A11: Mécénat d'entreprise — levée 3 (chalutier) | B11: =Ressources!B14 -> 0 | C11: =Ressources!C14 -> 0 | D11: =Ressources!D14 -> 2216500 | E11: =Ressources!E14 -> 0 | F11: =SUM(C11:E11) -> 2216500 | G11: =SUM(B11:E11) -> 2216500 | H11: Encaissée au T2 2028.
A12: Dons en numéraire non affectés | B12: =Ressources!B15 -> 0 | C12: =Ressources!C15 -> 0 | D12: =Ressources!D15 -> 0 | E12: =Ressources!E15 -> 0 | F12: =SUM(C12:E12) -> 0 | G12: =SUM(B12:E12) -> 0
A13: Dons en numéraire affectés à un programme | B13: =Ressources!B16 -> 0 | C13: =Ressources!C16 -> 0 | D13: =Ressources!D16 -> 0 | E13: =Ressources!E16 -> 0 | F13: =SUM(C13:E13) -> 0 | G13: =SUM(B13:E13) -> 0
A14: Mécénat en nature | B14: =Ressources!B17 -> 0 | C14: =Ressources!C17 -> 0 | D14: =Ressources!D17 -> 0 | E14: =Ressources!E17 -> 0 | F14: =SUM(C14:E14) -> 0 | G14: =SUM(B14:E14) -> 0
A15: Mécénat de compétences | B15: =Ressources!B18 -> 0 | C15: =Ressources!C18 -> 0 | D15: =Ressources!D18 -> 0 | E15: =Ressources!E18 -> 0 | F15: =SUM(C15:E15) -> 0 | G15: =SUM(B15:E15) -> 0
A16: Générosité du public | B16: =Ressources!B19 -> 0 | C16: =Ressources!C19 -> 0 | D16: =Ressources!D19 -> 0 | E16: =Ressources!E19 -> 0 | F16: =SUM(C16:E16) -> 0 | G16: =SUM(B16:E16) -> 0 | H16: Sous réserve de la déclaration préfectorale.
A17: Financement participatif | B17: =Ressources!B20 -> 0 | C17: =Ressources!C20 -> 0 | D17: =Ressources!D20 -> 0 | E17: =Ressources!E20 -> 0 | F17: =SUM(C17:E17) -> 0 | G17: =SUM(B17:E17) -> 0
A18: Dons individuels et prélèvements réguliers | B18: =Ressources!B21 -> 0 | C18: =Ressources!C21 -> 0 | D18: =Ressources!D21 -> 0 | E18: =Ressources!E21 -> 0 | F18: =SUM(C18:E18) -> 0 | G18: =SUM(B18:E18) -> 0
A19: Collecte événementielle et de filière | B19: =Ressources!B22 -> 0 | C19: =Ressources!C22 -> 0 | D19: =Ressources!D22 -> 0 | E19: =Ressources!E22 -> 0 | F19: =SUM(C19:E19) -> 0 | G19: =SUM(B19:E19) -> 0
A20: Micro-dons | B20: =Ressources!B23 -> 0 | C20: =Ressources!C23 -> 0 | D20: =Ressources!D23 -> 0 | E20: =Ressources!E23 -> 0 | F20: =SUM(C20:E20) -> 0 | G20: =SUM(B20:E20) -> 0
A21: Libéralités — donations et legs | B21: =Ressources!B24 -> 0 | C21: =Ressources!C24 -> 0 | D21: =Ressources!D24 -> 0 | E21: =Ressources!E24 -> 0 | F21: =SUM(C21:E21) -> 0 | G21: =SUM(B21:E21) -> 0
A22: Quote-part de frais de gestion sur les dons affectés | B22: =Ressources!B25 -> 0 | C22: =Ressources!C25 -> 0 | D22: =Ressources!D25 -> 0 | E22: =Ressources!E25 -> 0 | F22: =SUM(C22:E22) -> 0 | G22: =SUM(B22:E22) -> 0 | H22: Non négociée à ce jour.
A23: Recettes reversées par les structures | B23: =Ressources!B26 -> 0 | C23: =Ressources!C26 -> 0 | D23: =Ressources!D26 -> 0 | E23: =Ressources!E26 -> 0 | F23: =SUM(C23:E23) -> 0 | G23: =SUM(B23:E23) -> 0 | H23: Aucun revenu anticipé sur la période.
A24: Total des ressources | B24: =SUM(B7:B23) -> 172527.72 | C24: =SUM(C7:C23) -> 1598060.7 | D24: =SUM(D7:D23) -> 2217400 | E24: =SUM(E7:E23) -> 900 | F24: =SUM(C24:E24) -> 3816360.7 | G24: =SUM(B24:E24) -> 3988888.4
A25: dont ressources mobilisables — hors dotation | B25: =SUM(B8:B23) -> 157527.72 | C25: =SUM(C8:C23) -> 1568060.7 | D25: =SUM(D8:D23) -> 2217400 | E25: =SUM(E8:E23) -> 900 | F25: =SUM(C25:E25) -> 3786360.7 | G25: =SUM(B25:E25) -> 3943888.4
A27: EMPLOIS — A. ENVELOPPES DE PROGRAMME
A28: P1 — CONNAÎTRE ET SUIVRE LES MILIEUX MARINS | B28: =A_P1!B28 -> 0 | C28: =A_P1!C28 -> 150000 | D28: =A_P1!D28 -> 150000 | E28: =A_P1!E28 -> 150000 | F28: =SUM(C28:E28) -> 450000 | G28: =SUM(B28:E28) -> 450000
A29: P2 — RESTAURATION DES ÉCOSYSTÈMES | B29: =A_P2!B28 -> 0 | C29: =A_P2!C28 -> 800000 | D29: =A_P2!D28 -> 0 | E29: =A_P2!E28 -> 0 | F29: =SUM(C29:E29) -> 800000 | G29: =SUM(B29:E29) -> 800000
A30: P3 — DÉPOLLUTION DES MILIEUX | B30: =A_P3!B28 -> 43000 | C30: =A_P3!C28 -> 43000 | D30: =A_P3!D28 -> 43000 | E30: =A_P3!E28 -> 43000 | F30: =SUM(C30:E30) -> 129000 | G30: =SUM(B30:E30) -> 172000
A31: P4 — MODERNISATION DE LA FILIÈRE PÊCHE | B31: =A_P4!B28 -> 70000 | C31: =A_P4!C28 -> 108350 | D31: =A_P4!D28 -> 2048350 | E31: =A_P4!E28 -> 67850 | F31: =SUM(C31:E31) -> 2224550 | G31: =SUM(B31:E31) -> 2294550
A32: A — Total des enveloppes de programme | B32: =SUM(B28:B31) -> 113000 | C32: =SUM(C28:C31) -> 1101350 | D32: =SUM(D28:D31) -> 2241350 | E32: =SUM(E28:E31) -> 260850 | F32: =SUM(C32:E32) -> 3603550 | G32: =SUM(B32:E32) -> 3716550
A34: EMPLOIS — B. MOYENS COMMUNS
A35: B — Total des moyens communs | B35: ='B · Moyens communs'!B10 -> 2120 | C35: ='B · Moyens communs'!C10 -> 9707.23 | D35: ='B · Moyens communs'!D10 -> 25663.52 | E35: ='B · Moyens communs'!E10 -> 35216.28 | F35: =SUM(C35:E35) -> 70587.03 | G35: =SUM(B35:E35) -> 72707.03
A37: EMPLOIS — C. FRAIS DE FONCTIONNEMENT
A38: C — Total des frais de fonctionnement | B38: ='C · Fonctionnement'!B17 -> 300 | C38: ='C · Fonctionnement'!C17 -> 32325.49 | D38: ='C · Fonctionnement'!D17 -> 59875.72 | E38: ='C · Fonctionnement'!E17 -> 62130.17 | F38: =SUM(C38:E38) -> 154331.38 | G38: =SUM(B38:E38) -> 154631.38
A40: ÉQUILIBRE
A41: Total des emplois — A + B + C | B41: =B32+B35+B38 -> 115420 | C41: =C32+C35+C38 -> 1143382.7 | D41: =D32+D35+D38 -> 2326889.2 | E41: =E32+E35+E38 -> 358196.45 | F41: =SUM(C41:E41) -> 3828468.4 | G41: =SUM(B41:E41) -> 3943888.4
A42: Résultat de l'exercice | B42: =B25-B41 -> 42107.72 | C42: =C25-C41 -> 424677.97 | D42: =D25-D41 -> -109489.24 | E42: =E25-E41 -> -357296.45 | F42: =SUM(C42:E42) -> -42107.72 | G42: =SUM(B42:E42) -> 0 | H42: Calculé sur les ressources mobilisables : la dotation non consomptible en est exclue.
A43: Réserve non affectée, cumulée en fin d'exercice | B43: =B42 -> 42107.72 | C43: =B43+C42 -> 466785.69 | D43: =C43+D42 -> 357296.45 | E43: =D43+E42 -> 0
A45: POUR MÉMOIRE — HORS BUDGET DU FONDS
A46: Subventions publiques portées par l'association | B46: =Synthèse!B31 -> 0 | C46: =Synthèse!C31 -> 29607.11 | D46: =Synthèse!D31 -> 55110.94 | E46: =Synthèse!E31 -> 55804.3 | F46: =SUM(C46:E46) -> 140522.35 | G46: =SUM(B46:E46) -> 140522.35
A47: Montants reversés aux professionnels via Mare Services | B47: =Synthèse!B33 -> 0 | C47: =Synthèse!C33 -> 28480 | D47: =Synthèse!D33 -> 28480 | E47: =Synthèse!E33 -> 28480 | F47: =SUM(C47:E47) -> 85440 | G47: =SUM(B47:E47) -> 85440

Sheet A_P1
A1: P1 — CONNAÎTRE ET SUIVRE LES MILIEUX MARINS
A2: Budget du programme — ressources, emplois par voie d'intervention, revenus réinjectables.
A3: Le programme dote la structure de valorisation des données ; la part conservée par la plateforme lui est réaffectée.
A5: Poste | B5: 2026 | C5: 2027 | D5: 2028 | E5: 2029 | F5: Total 3 ans 2027-2029 | G5: Total période 2026-2029 | H5: Source / commentaire
A6: RESSOURCES DU PROGRAMME
A7: Produits financiers de la dotation affectés au programme | B7: 0 | C7: 0 | D7: 0 | E7: 0 | F7: =SUM(C7:E7) -> 0 | G7: =SUM(B7:E7) -> 0 | H7: La dotation est non consomptible : seuls ses produits peuvent être affectés.
A8: Revenus des structures et start-up du programme | B8: 0 | C8: 0 | D8: 0 | E8: 0 | F8: =SUM(C8:E8) -> 0 | G8: =SUM(B8:E8) -> 0 | H8: Redevances, licences, dividendes, produits de cession. Aucun revenu anticipé sur 2026-2029.
A9: Quote-part reversée par la plateforme de services | B9: 0 | C9: 0 | D9: 0 | E9: 0 | F9: =SUM(C9:E9) -> 0 | G9: =SUM(B9:E9) -> 0 | H9: Solde de la commission de 20 % après couverture des charges de la plateforme.
A10: Report du solde de l'exercice précédent — réinjection | B10: 0 | C10: =MAX(0,B31) -> 0 | D10: =MAX(0,C31) -> 0 | E10: =MAX(0,D31) -> 0 | F10: =SUM(C10:E10) -> 0 | G10: =SUM(B10:E10) -> 0 | H10: Réserve non consommée de l'exercice précédent, réinjectée dans le programme.
A11: Mécénat et dons affectés au programme — besoin de collecte | B11: =MAX(0,B28-B7-B8-B9-B10) -> 0 | C11: =MAX(0,C28-C7-C8-C9-C10) -> 150000 | D11: =MAX(0,D28-D7-D8-D9-D10) -> 150000 | E11: =MAX(0,E28-E7-E8-E9-E10) -> 150000 | F11: =SUM(C11:E11) -> 450000 | G11: =SUM(B11:E11) -> 450000 | H11: Calculé : ce qu'il reste à lever pour le programme une fois les autres ressources déduites.
A12: TOTAL DES RESSOURCES | B12: =SUM(B7:B11) -> 0 | C12: =SUM(C7:C11) -> 150000 | D12: =SUM(D7:D11) -> 150000 | E12: =SUM(E7:E11) -> 150000 | F12: =SUM(C12:E12) -> 450000 | G12: =SUM(B12:E12) -> 450000
A14: EMPLOIS — VOIE REDISTRIBUTEUR
A15: Cocktail chimique du Rhône — subvention au porteur | B15: 0 | C15: 150000 | D15: 150000 | E15: 150000 | F15: =SUM(C15:E15) -> 450000 | G15: =SUM(B15:E15) -> 450000 | H15: 3 × 150 000 € (T2 2027, 2028, 2029). Voie redistributeur : projet conduit par un tiers.
A16: Subvention à un tiers porteur — à renseigner | B16: 0 | C16: 0 | D16: 0 | E16: 0 | F16: =SUM(C16:E16) -> 0 | G16: =SUM(B16:E16) -> 0
A17: Subvention à un tiers porteur — à renseigner | B17: 0 | C17: 0 | D17: 0 | E17: 0 | F17: =SUM(C17:E17) -> 0 | G17: =SUM(B17:E17) -> 0
A18: Prises de participation minoritaires | B18: 0 | C18: 0 | D18: 0 | E18: 0 | F18: =SUM(C18:E18) -> 0 | G18: =SUM(B18:E18) -> 0 | H18: À vérifier avec Fidal : une prise de participation n'est pas une redistribution au sens de l'article 140.
A19: Sous-total voie redistributeur | B19: =SUM(B15:B18) -> 0 | C19: =SUM(C15:C18) -> 150000 | D19: =SUM(D15:D18) -> 150000 | E19: =SUM(E15:E18) -> 150000 | F19: =SUM(C19:E19) -> 450000 | G19: =SUM(B19:E19) -> 450000
A21: EMPLOIS — VOIE OPÉRATEUR
A22: Commande de prestation sur cahier des charges — à renseigner | B22: 0 | C22: 0 | D22: 0 | E22: 0 | F22: =SUM(C22:E22) -> 0 | G22: =SUM(B22:E22) -> 0
A23: Commande de prestation sur cahier des charges — à renseigner | B23: 0 | C23: 0 | D23: 0 | E23: 0 | F23: =SUM(C23:E23) -> 0 | G23: =SUM(B23:E23) -> 0
A24: Création de société et participation majoritaire | B24: 0 | C24: 0 | D24: 0 | E24: 0 | F24: =SUM(C24:E24) -> 0 | G24: =SUM(B24:E24) -> 0
A25: Achats d'équipements au titre du programme | B25: 0 | C25: 0 | D25: 0 | E25: 0 | F25: =SUM(C25:E25) -> 0 | G25: =SUM(B25:E25) -> 0 | H25: Acquis par le fonds puis transférés à la structure de détention du matériel.
A26: Sous-total voie opérateur | B26: =SUM(B22:B25) -> 0 | C26: =SUM(C22:C25) -> 0 | D26: =SUM(D22:D25) -> 0 | E26: =SUM(E22:E25) -> 0 | F26: =SUM(C26:E26) -> 0 | G26: =SUM(B26:E26) -> 0
A28: TOTAL DES EMPLOIS DU PROGRAMME | B28: =B19+B26 -> 0 | C28: =C19+C26 -> 150000 | D28: =D19+D26 -> 150000 | E28: =E19+E26 -> 150000 | F28: =SUM(C28:E28) -> 450000 | G28: =SUM(B28:E28) -> 450000
A30: ÉQUILIBRE
A31: Solde de l'exercice | B31: =B12-B28 -> 0 | C31: =C12-C28 -> 0 | D31: =D12-D28 -> 0 | E31: =E12-E28 -> 0 | F31: =SUM(C31:E31) -> 0 | G31: =SUM(B31:E31) -> 0 | H31: Positif : ressources non consommées, réinjectées l'exercice suivant.
A33: Enveloppe de référence du programme | G33: 450000
A34: Écart entre l'enveloppe et les engagements datés | G34: =G33-G28 -> 0

Sheet A_P2
A1: P2 — RESTAURATION DES ÉCOSYSTÈMES
A2: Budget du programme — ressources, emplois par voie d'intervention, revenus réinjectables.
A3: Volet A co-gestion d'AMP (pêcheur prestataire, prélèvement de 20 %) et volet B récifs portés par une start-up.
A5: Poste | B5: 2026 | C5: 2027 | D5: 2028 | E5: 2029 | F5: Total 3 ans 2027-2029 | G5: Total période 2026-2029
A6: RESSOURCES DU PROGRAMME
A7: Produits financiers de la dotation affectés au programme | B7: 0 | C7: 0 | D7: 0 | E7: 0 | F7: =SUM(C7:E7) -> 0 | G7: =SUM(B7:E7) -> 0
A8: Revenus des structures et start-up du programme | B8: 0 | C8: 0 | D8: 0 | E8: 0 | F8: =SUM(C8:E8) -> 0 | G8: =SUM(B8:E8) -> 0
A9: Quote-part reversée par la plateforme de services | B9: 0 | C9: 0 | D9: 0 | E9: 0 | F9: =SUM(C9:E9) -> 0 | G9: =SUM(B9:E9) -> 0
A10: Report du solde de l'exercice précédent — réinjection | B10: 0 | C10: =MAX(0,B31) -> 0 | D10: =MAX(0,C31) -> 0 | E10: =MAX(0,D31) -> 0 | F10: =SUM(C10:E10) -> 0 | G10: =SUM(B10:E10) -> 0
A11: Mécénat et dons affectés au programme — besoin de collecte | B11: =MAX(0,B28-B7-B8-B9-B10) -> 0 | C11: =MAX(0,C28-C7-C8-C9-C10) -> 800000 | D11: =MAX(0,D28-D7-D8-D9-D10) -> 0 | E11: =MAX(0,E28-E7-E8-E9-E10) -> 0 | F11: =SUM(C11:E11) -> 800000 | G11: =SUM(B11:E11) -> 800000
A12: TOTAL DES RESSOURCES | B12: =SUM(B7:B11) -> 0 | C12: =SUM(C7:C11) -> 800000 | D12: =SUM(D7:D11) -> 0 | E12: =SUM(E7:E11) -> 0 | F12: =SUM(C12:E12) -> 800000 | G12: =SUM(B12:E12) -> 800000
A14: EMPLOIS — VOIE REDISTRIBUTEUR
A15: Fishwind — subvention au porteur | B15: 0 | D15: 0 | E15: 0 | F15: =SUM(C15:E15) -> 0 | G15: =SUM(B15:E15) -> 0
A16: Subvention à un tiers porteur — à renseigner | B16: 0 | C16: 0 | D16: 0 | E16: 0 | F16: =SUM(C16:E16) -> 0 | G16: =SUM(B16:E16) -> 0
A17: Subvention à un tiers porteur — à renseigner | B17: 0 | C17: 0 | D17: 0 | E17: 0 | F17: =SUM(C17:E17) -> 0 | G17: =SUM(B17:E17) -> 0
A18: Prises de participation minoritaires | B18: 0 | C18: 0 | D18: 0 | E18: 0 | F18: =SUM(C18:E18) -> 0 | G18: =SUM(B18:E18) -> 0
A19: Sous-total voie redistributeur | B19: =SUM(B15:B18) -> 0 | C19: =SUM(C15:C18) -> 0 | D19: =SUM(D15:D18) -> 0 | E19: =SUM(E15:E18) -> 0 | F19: =SUM(C19:E19) -> 0 | G19: =SUM(B19:E19) -> 0
A21: EMPLOIS — VOIE OPÉRATEUR
A22: Fishwind — prise de participation start-up | B22: 0 | C22: 800000 | D22: 0 | E22: 0 | F22: =SUM(C22:E22) -> 800000 | G22: =SUM(B22:E22) -> 800000
A23: Commande de prestation sur cahier des charges — à renseigner | B23: 0 | C23: 0 | D23: 0 | E23: 0 | F23: =SUM(C23:E23) -> 0 | G23: =SUM(B23:E23) -> 0
A24: Création de société et participation majoritaire | B24: 0 | C24: 0 | D24: 0 | E24: 0 | F24: =SUM(C24:E24) -> 0 | G24: =SUM(B24:E24) -> 0
A25: Achats d'équipements au titre du programme | B25: 0 | C25: 0 | D25: 0 | E25: 0 | F25: =SUM(C25:E25) -> 0 | G25: =SUM(B25:E25) -> 0
A26: Sous-total voie opérateur | B26: =SUM(B22:B25) -> 0 | C26: =SUM(C22:C25) -> 800000 | D26: =SUM(D22:D25) -> 0 | E26: =SUM(E22:E25) -> 0 | F26: =SUM(C26:E26) -> 800000 | G26: =SUM(B26:E26) -> 800000
A28: TOTAL DES EMPLOIS DU PROGRAMME | B28: =B19+B26 -> 0 | C28: =C19+C26 -> 800000 | D28: =D19+D26 -> 0 | E28: =E19+E26 -> 0 | F28: =SUM(C28:E28) -> 800000 | G28: =SUM(B28:E28) -> 800000
A30: ÉQUILIBRE
A31: Solde de l'exercice | B31: =B12-B28 -> 0 | C31: =C12-C28 -> 0 | D31: =D12-D28 -> 0 | E31: =E12-E28 -> 0 | F31: =SUM(C31:E31) -> 0 | G31: =SUM(B31:E31) -> 0
A33: Enveloppe de référence du programme | G33: 800000
A34: Écart entre l'enveloppe et les engagements datés | G34: =G33-G28 -> 0

Sheet A_P3
A1: P3 — DÉPOLLUTION DES MILIEUX
A2: Budget du programme — ressources, emplois par voie d'intervention, revenus réinjectables.
A3: Rémunération de la flotte pour le plastique remonté. Commande passée par le fonds, exécutée par les professionnels.
A5: Poste | B5: 2026 | C5: 2027 | D5: 2028 | E5: 2029 | F5: Total 3 ans 2027-2029 | G5: Total période 2026-2029 | H5: Source / commentaire
A6: RESSOURCES DU PROGRAMME
A7: Produits financiers de la dotation affectés au programme | B7: 0 | C7: 0 | D7: 0 | E7: 0 | F7: =SUM(C7:E7) -> 0 | G7: =SUM(B7:E7) -> 0 | H7: La dotation est non consomptible : seuls ses produits peuvent être affectés.
A8: Revenus des structures et start-up du programme | B8: 0 | C8: 0 | D8: 0 | E8: 0 | F8: =SUM(C8:E8) -> 0 | G8: =SUM(B8:E8) -> 0 | H8: Redevances, licences, dividendes, produits de cession. Aucun revenu anticipé sur 2026-2029.
A9: Quote-part reversée par la plateforme de services | B9: 0 | C9: 0 | D9: 0 | E9: 0 | F9: =SUM(C9:E9) -> 0 | G9: =SUM(B9:E9) -> 0 | H9: Solde de la commission de 20 % après couverture des charges de la plateforme.
A10: Report du solde de l'exercice précédent — réinjection | B10: 0 | C10: =MAX(0,B31) -> 0 | D10: =MAX(0,C31) -> 0 | E10: =MAX(0,D31) -> 0 | F10: =SUM(C10:E10) -> 0 | G10: =SUM(B10:E10) -> 0 | H10: Réserve non consommée de l'exercice précédent, réinjectée dans le programme.
A11: Mécénat et dons affectés au programme — besoin de collecte | B11: =MAX(0,B28-B7-B8-B9-B10) -> 43000 | C11: =MAX(0,C28-C7-C8-C9-C10) -> 43000 | D11: =MAX(0,D28-D7-D8-D9-D10) -> 43000 | E11: =MAX(0,E28-E7-E8-E9-E10) -> 43000 | F11: =SUM(C11:E11) -> 129000 | G11: =SUM(B11:E11) -> 172000 | H11: Calculé : ce qu'il reste à lever pour le programme une fois les autres ressources déduites.
A12: TOTAL DES RESSOURCES | B12: =SUM(B7:B11) -> 43000 | C12: =SUM(C7:C11) -> 43000 | D12: =SUM(D7:D11) -> 43000 | E12: =SUM(E7:E11) -> 43000 | F12: =SUM(C12:E12) -> 129000 | G12: =SUM(B12:E12) -> 172000
A14: EMPLOIS — VOIE REDISTRIBUTEUR
A15: Subvention à un tiers porteur — à renseigner | B15: 0 | C15: 0 | D15: 0 | E15: 0 | F15: =SUM(C15:E15) -> 0 | G15: =SUM(B15:E15) -> 0
A16: Subvention à un tiers porteur — à renseigner | B16: 0 | C16: 0 | D16: 0 | E16: 0 | F16: =SUM(C16:E16) -> 0 | G16: =SUM(B16:E16) -> 0
A17: Subvention à un tiers porteur — à renseigner | B17: 0 | C17: 0 | D17: 0 | E17: 0 | F17: =SUM(C17:E17) -> 0 | G17: =SUM(B17:E17) -> 0
A18: Prises de participation minoritaires | B18: 0 | C18: 0 | D18: 0 | E18: 0 | F18: =SUM(C18:E18) -> 0 | G18: =SUM(B18:E18) -> 0 | H18: À vérifier avec Fidal : une prise de participation n'est pas une redistribution au sens de l'article 140.
A19: Sous-total voie redistributeur | B19: =SUM(B15:B18) -> 0 | C19: =SUM(C15:C18) -> 0 | D19: =SUM(D15:D18) -> 0 | E19: =SUM(E15:E18) -> 0 | F19: =SUM(C19:E19) -> 0 | G19: =SUM(B19:E19) -> 0
A21: EMPLOIS — VOIE OPÉRATEUR
A22: Mare Collect — rémunération des professionnels, sur cahier des charges | B22: 43000 | C22: 43000 | D22: 43000 | E22: 43000 | F22: =SUM(C22:E22) -> 129000 | G22: =SUM(B22:E22) -> 172000 | H22: 4 × 43 000 € (T4 2026, 2027, 2028, 2029). Voie opérateur : commande de prestation via Mare Services.
A23: Commande de prestation sur cahier des charges — à renseigner | B23: 0 | C23: 0 | D23: 0 | E23: 0 | F23: =SUM(C23:E23) -> 0 | G23: =SUM(B23:E23) -> 0
A24: Création de société et participation majoritaire | B24: 0 | C24: 0 | D24: 0 | E24: 0 | F24: =SUM(C24:E24) -> 0 | G24: =SUM(B24:E24) -> 0
A25: Achats d'équipements au titre du programme | B25: 0 | C25: 0 | D25: 0 | E25: 0 | F25: =SUM(C25:E25) -> 0 | G25: =SUM(B25:E25) -> 0 | H25: Acquis par le fonds puis transférés à la structure de détention du matériel.
A26: Sous-total voie opérateur | B26: =SUM(B22:B25) -> 43000 | C26: =SUM(C22:C25) -> 43000 | D26: =SUM(D22:D25) -> 43000 | E26: =SUM(E22:E25) -> 43000 | F26: =SUM(C26:E26) -> 129000 | G26: =SUM(B26:E26) -> 172000
A28: TOTAL DES EMPLOIS DU PROGRAMME | B28: =B19+B26 -> 43000 | C28: =C19+C26 -> 43000 | D28: =D19+D26 -> 43000 | E28: =E19+E26 -> 43000 | F28: =SUM(C28:E28) -> 129000 | G28: =SUM(B28:E28) -> 172000
A30: ÉQUILIBRE
A31: Solde de l'exercice | B31: =B12-B28 -> 0 | C31: =C12-C28 -> 0 | D31: =D12-D28 -> 0 | E31: =E12-E28 -> 0 | F31: =SUM(C31:E31) -> 0 | G31: =SUM(B31:E31) -> 0 | H31: Positif : ressources non consommées, réinjectées l'exercice suivant.
A33: Enveloppe de référence du programme | G33: 172000
A34: Écart entre l'enveloppe et les engagements datés | G34: =G33-G28 -> 0

Sheet A_P4
A1: P4 — MODERNISATION DE LA FILIÈRE PÊCHE
A2: Budget du programme — ressources, emplois par voie d'intervention, revenus réinjectables.
A3: Volet A navires (Mare Nova) et volet B engins sélectifs (SmartSnap).
A5: Poste | B5: 2026 | C5: 2027 | D5: 2028 | E5: 2029 | F5: Total 3 ans 2027-2029 | G5: Total période 2026-2029
A6: RESSOURCES DU PROGRAMME
A7: Produits financiers de la dotation affectés au programme | B7: 0 | C7: 0 | D7: 0 | E7: 0 | F7: =SUM(C7:E7) -> 0 | G7: =SUM(B7:E7) -> 0
A8: Revenus des structures et start-up du programme | B8: 0 | C8: 0 | D8: 0 | E8: 0 | F8: =SUM(C8:E8) -> 0 | G8: =SUM(B8:E8) -> 0
A9: Quote-part reversée par la plateforme de services | B9: 0 | C9: 0 | D9: 0 | E9: 0 | F9: =SUM(C9:E9) -> 0 | G9: =SUM(B9:E9) -> 0
A10: Report du solde de l'exercice précédent — réinjection | B10: 0 | C10: =MAX(0,B31) -> 0 | D10: =MAX(0,C31) -> 0 | E10: =MAX(0,D31) -> 0 | F10: =SUM(C10:E10) -> 0 | G10: =SUM(B10:E10) -> 0
A11: Mécénat et dons affectés au programme — besoin de collecte | B11: =MAX(0,B28-B7-B8-B9-B10) -> 70000 | C11: =MAX(0,C28-C7-C8-C9-C10) -> 108350 | D11: =MAX(0,D28-D7-D8-D9-D10) -> 2048350 | E11: =MAX(0,E28-E7-E8-E9-E10) -> 67850 | F11: =SUM(C11:E11) -> 2224550 | G11: =SUM(B11:E11) -> 2294550
A12: TOTAL DES RESSOURCES | B12: =SUM(B7:B11) -> 70000 | C12: =SUM(C7:C11) -> 108350 | D12: =SUM(D7:D11) -> 2048350 | E12: =SUM(E7:E11) -> 67850 | F12: =SUM(C12:E12) -> 2224550 | G12: =SUM(B12:E12) -> 2294550
A14: EMPLOIS — VOIE REDISTRIBUTEUR
A15: SmartSnap — subvention au porteur (CNRS, Ifremer) | B15: 0 | C15: 108350 | D15: 48350 | E15: 67850 | F15: =SUM(C15:E15) -> 224550 | G15: =SUM(B15:E15) -> 224550
A16: Construction du chalutier — subvention au porteur | B16: 0 | C16: 0 | D16: 2000000 | E16: 0 | F16: =SUM(C16:E16) -> 2000000 | G16: =SUM(B16:E16) -> 2000000
A17: Subvention à un tiers porteur — à renseigner | B17: 0 | C17: 0 | D17: 0 | E17: 0 | F17: =SUM(C17:E17) -> 0 | G17: =SUM(B17:E17) -> 0
A18: Prises de participation minoritaires | B18: 0 | C18: 0 | D18: 0 | E18: 0 | F18: =SUM(C18:E18) -> 0 | G18: =SUM(B18:E18) -> 0
A19: Sous-total voie redistributeur | B19: =SUM(B15:B18) -> 0 | C19: =SUM(C15:C18) -> 108350 | D19: =SUM(D15:D18) -> 2048350 | E19: =SUM(E15:E18) -> 67850 | F19: =SUM(C19:E19) -> 2224550 | G19: =SUM(B19:E19) -> 2224550
A21: EMPLOIS — VOIE OPÉRATEUR
A22: Étude de conception du chalutier — commande de prestation | B22: 70000 | C22: 0 | D22: 0 | E22: 0 | F22: =SUM(C22:E22) -> 0 | G22: =SUM(B22:E22) -> 70000
A23: Commande de prestation sur cahier des charges — à renseigner | B23: 0 | C23: 0 | D23: 0 | E23: 0 | F23: =SUM(C23:E23) -> 0 | G23: =SUM(B23:E23) -> 0
A24: Création de société et participation majoritaire | B24: 0 | C24: 0 | D24: 0 | E24: 0 | F24: =SUM(C24:E24) -> 0 | G24: =SUM(B24:E24) -> 0
A25: Achats d'équipements au titre du programme | B25: 0 | C25: 0 | D25: 0 | E25: 0 | F25: =SUM(C25:E25) -> 0 | G25: =SUM(B25:E25) -> 0
A26: Sous-total voie opérateur | B26: =SUM(B22:B25) -> 70000 | C26: =SUM(C22:C25) -> 0 | D26: =SUM(D22:D25) -> 0 | E26: =SUM(E22:E25) -> 0 | F26: =SUM(C26:E26) -> 0 | G26: =SUM(B26:E26) -> 70000
A28: TOTAL DES EMPLOIS DU PROGRAMME | B28: =B19+B26 -> 70000 | C28: =C19+C26 -> 108350 | D28: =D19+D26 -> 2048350 | E28: =E19+E26 -> 67850 | F28: =SUM(C28:E28) -> 2224550 | G28: =SUM(B28:E28) -> 2294550
A30: ÉQUILIBRE
A31: Solde de l'exercice | B31: =B12-B28 -> 0 | C31: =C12-C28 -> 0 | D31: =D12-D28 -> 0 | E31: =E12-E28 -> 0 | F31: =SUM(C31:E31) -> 0 | G31: =SUM(B31:E31) -> 0
A33: Enveloppe de référence du programme | G33: 2294550
A34: Écart entre l'enveloppe et les engagements datés | G34: =G33-G28 -> 0

Sheet B · Moyens communs
A1: BLOC B — ENVELOPPE DE MOYENS COMMUNS
A2: Ce qui sert l'ensemble des programmes sans pouvoir être rattaché à l'un d'eux.
A3: Deux natures de dépense : l'apport de démarrage des structures économiques, et le reste à charge de la part non publique du budget de l'association Mare Durabilis, versé par le fonds une fois déduits le financement public (80 % de l’assiette éligible), les refacturations et l'autofinancement de l'association (1 %).
A5: Poste | B5: 2026 | C5: 2027 | D5: 2028 | E5: 2029 | F5: Total 3 ans 2027-2029 | G5: Total période 2026-2029 | H5: Source / commentaire
A6: POSTES
A7: B.1 · Plateforme Mare Services | B7: 0 | C7: 188.49 | D7: 6276.72 | E7: 6517.17 | F7: =SUM(C7:E7) -> 12982.38 | G7: =SUM(B7:E7) -> 12982.38 | H7: Aucune charge en 2026 (plateforme créée en 2027). La commission de 20 % (7 120 €) ne couvre pas les charges : outils 600 €/an Stripe 33 €/an (pesca-tourisme seulement) refacturation par l'association de 0 20 ETP et de 20 % des moyens matériels constitution 400 € en 2027. Le fonds couvre le déficit : 919 € 6 636 € 6 882 €.
A8: B.2 · Structure de détention du matériel | B8: 2120 | C8: 0 | D8: 0 | E8: 0 | F8: =SUM(C8:E8) -> 0 | G8: =SUM(B8:E8) -> 2120 | H8: Apport de démarrage 2 120 €. Aucun achat d'équipement prévu.
A9: B.3 · Reste à charge de la part non publique — association Mare Durabilis | B9: 0 | C9: 9518.74 | D9: 19386.8 | E9: 28699.11 | F9: =SUM(C9:E9) -> 57604.65 | G9: =SUM(B9:E9) -> 57604.65 | H9: Reste à charge de l'association après financement public (80 % de l'assiette éligible FEAMPA), refacturations et autofinancement (1 %), y compris les intérêts non éligibles de l'avance de trésorerie. Repris du budget de fonctionnement ASSO.
A10: B — TOTAL DES MOYENS COMMUNS | B10: =SUM(B7:B9) -> 2120 | C10: =SUM(C7:C9) -> 9707.23 | D10: =SUM(D7:D9) -> 25663.52 | E10: =SUM(E7:E9) -> 35216.28 | F10: =SUM(C10:E10) -> 70587.03 | G10: =SUM(B10:E10) -> 72707.03
A12: Moyens communs portés à 73 430 € sur la période : apport de démarrage de la structure de détention du matériel, déficit d'exploitation de Mare Services et reste à charge de l'association. Ressources allouées par le conseil, provenant de la même source que les frais de fonctionnement et les enveloppes de programme : les levées de mécénat non affecté.

Sheet C · Fonctionnement
A1: BLOC C — FRAIS DE FONCTIONNEMENT DU FONDS
A2: Distinct du budget de gouvernance porté par l'association.
A5: Poste | B5: 2026 | C5: 2027 | D5: 2028 | E5: 2029 | F5: Total 3 ans 2027-2029 | G5: Total période 2026-2029 | H5: Source / commentaire
A6: POSTES
A7: Quote-part du chef de projet refacturée par l'association | B7: 0 | C7: 5685.66 | D7: 11598.75 | E7: 11830.72 | F7: =SUM(C7:E7) -> 29115.13 | G7: =SUM(B7:E7) -> 29115.13 | H7: 20 % du coût complet du chef de projet : salaire chargé (base 55 000 € en 2026, revalorisation de 2 %/an), mutuelle et prévoyance.
A8: Honoraires du commissaire aux comptes | B8: 0 | C8: 8000 | D8: 8000 | E8: 8000 | F8: =SUM(C8:E8) -> 24000 | G8: =SUM(B8:E8) -> 24000 | H8: Obligatoire dès 10 000 € de ressources.
A9: Expertise comptable et tenue des comptes | B9: 0 | C9: 3000 | D9: 4000 | E9: 6000 | F9: =SUM(C9:E9) -> 13000 | G9: =SUM(B9:E9) -> 13000
A10: Honoraires juridiques et fiscaux propres au fonds | B10: 0 | C10: 0 | D10: 15000 | E10: 15000 | F10: =SUM(C10:E10) -> 30000 | G10: =SUM(B10:E10) -> 30000
A11: Frais bancaires et gestion des placements | B11: 300 | C11: 500 | D11: 1000 | E11: 1000 | F11: =SUM(C11:E11) -> 2500 | G11: =SUM(B11:E11) -> 2800 | H11: À compter de la création du fonds.
A12: Frais de recherche de fonds | B12: 0 | C12: 0 | D12: 10000 | E12: 10000 | F12: =SUM(C12:E12) -> 20000 | G12: =SUM(B12:E12) -> 20000
A13: Quote-part des moyens matériels refacturée par l'association | B13: 0 | C13: 589.83 | D13: 1164.97 | E13: 1173.45 | F13: =SUM(C13:E13) -> 2928.25 | G13: =SUM(B13:E13) -> 2928.25 | H13: 20 % des charges locatives, multirisque, télécommunications et fournitures courantes de l'association (hors locaux et mobilier, portés par le fonds).
A14: Locaux mis à disposition de l'association (loyer, TEOM, charges) | B14: 0 | C14: 4350 | D14: 9012 | E14: 9026 | F14: =SUM(C14:E14) -> 22388 | G14: =SUM(B14:E14) -> 22388 | H14: Bail porté par le fonds (700 €/mois, plus TEOM et charges) ; bureau mis à disposition de l'association par convention. Hors assiette FEAMPA (coût indirect couvert par le forfait de 15 %).
A15: Mobilier de première installation | B15: 0 | C15: 10000 | D15: 0 | E15: 0 | F15: =SUM(C15:E15) -> 10000 | G15: =SUM(B15:E15) -> 10000 | H15: Bureau, sièges, rangements. Acquis par le fonds et mis à disposition.
A16: Frais de représentation (réceptions de partenaires et de mécènes) | B16: 0 | C16: 200 | D16: 100 | E16: 100 | F16: =SUM(C16:E16) -> 400 | G16: =SUM(B16:E16) -> 400 | H16: Transféré du budget de l'association : non éligible au FEAMPA. Réceptions organisées au nom du fonds, sur ses ressources privées.
A17: C — TOTAL DES FRAIS DE FONCTIONNEMENT | B17: =SUM(B7:B16) -> 300 | C17: =SUM(C7:C16) -> 32325.49 | D17: =SUM(D7:D16) -> 59875.72 | E17: =SUM(E7:E16) -> 62130.17 | F17: =SUM(C17:E17) -> 154331.38 | G17: =SUM(B17:E17) -> 154631.38
A19: Frais de fonctionnement portés à 156 085 € sur la période, dont les locaux et le mobilier mis à disposition de l'association et les frais de représentation. Deux lignes sont refacturées par l'association — le temps du chef de projet et les moyens matériels.

Sheet Ressources
A1: RESSOURCES DU FONDS
A2: Circuit privé uniquement. Aucune ressource publique ne peut entrer dans le fonds de dotation.
A5: Poste | B5: 2026 | C5: 2027 | D5: 2028 | E5: 2029 | F5: Total 3 ans 2027-2029 | G5: Total période 2026-2029
A6: DOTATION NON CONSOMPTIBLE — NON MOBILISABLE
A7: Versements à la dotation | B7: 15000 | C7: 30000 | D7: 0 | E7: 0 | F7: =SUM(C7:E7) -> 30000 | G7: =SUM(B7:E7) -> 45000
A8: Capital de dotation en fin d'exercice | B8: =B7 -> 15000 | C8: =B8+C7 -> 45000 | D8: =C8+D7 -> 45000 | E8: =D8+E7 -> 45000 | F8: — | G8: —
A10: RESSOURCES MOBILISABLES
A11: Revenus de la dotation — produits de placement | B11: 75 | C11: 525 | D11: 900 | E11: 900 | F11: =SUM(C11:E11) -> 2325 | G11: =SUM(B11:E11) -> 2400
A12: Mécénat d'entreprise — levée 1 (amorçage : Mare Collect 2026, étude de conception, blocs B et C 2026-2027) | B12: 157452.72 | C12: 0 | D12: 0 | E12: 0 | F12: =SUM(C12:E12) -> 0 | G12: =SUM(B12:E12) -> 157452.72
A13: Mécénat d'entreprise — levée 2 (amorçage des programmes ; Mare Collect 2027-2029 ; blocs B et C 2028-2029) | B13: 0 | C13: 1567535.7 | D13: 0 | E13: 0 | F13: =SUM(C13:E13) -> 1567535.7 | G13: =SUM(B13:E13) -> 1567535.7
A14: Mécénat d'entreprise — levée 3 (chalutier et fin de période) | B14: 0 | C14: 0 | D14: 2216500 | E14: 0 | F14: =SUM(C14:E14) -> 2216500 | G14: =SUM(B14:E14) -> 2216500
A15: Dons en numéraire non affectés | B15: 0 | C15: 0 | D15: 0 | E15: 0 | F15: =SUM(C15:E15) -> 0 | G15: =SUM(B15:E15) -> 0
A16: Dons en numéraire affectés à un programme | B16: 0 | C16: 0 | D16: 0 | E16: 0 | F16: =SUM(C16:E16) -> 0 | G16: =SUM(B16:E16) -> 0
A17: Mécénat en nature | B17: 0 | C17: 0 | D17: 0 | E17: 0 | F17: =SUM(C17:E17) -> 0 | G17: =SUM(B17:E17) -> 0
A18: Mécénat de compétences | B18: 0 | C18: 0 | D18: 0 | E18: 0 | F18: =SUM(C18:E18) -> 0 | G18: =SUM(B18:E18) -> 0
A19: Générosité du public | B19: 0 | C19: 0 | D19: 0 | E19: 0 | F19: =SUM(C19:E19) -> 0 | G19: =SUM(B19:E19) -> 0
A20: Financement participatif | B20: 0 | C20: 0 | D20: 0 | E20: 0 | F20: =SUM(C20:E20) -> 0 | G20: =SUM(B20:E20) -> 0
A21: Dons individuels et prélèvements réguliers | B21: 0 | C21: 0 | D21: 0 | E21: 0 | F21: =SUM(C21:E21) -> 0 | G21: =SUM(B21:E21) -> 0
A22: Collecte événementielle et de filière | B22: 0 | C22: 0 | D22: 0 | E22: 0 | F22: =SUM(C22:E22) -> 0 | G22: =SUM(B22:E22) -> 0
... A26: Recettes reversées par les structures | B26: 0 | C26: 0 | D26: 0 | E26: 0 | F26: =SUM(C26:E26) -> 0 | G26: =SUM(B26:E26) -> 0
A27: TOTAL DES RESSOURCES MOBILISABLES | B27: =SUM(B11:B26) -> 157527.72 | C27: =SUM(C11:C26) -> 1568060.7 | D27: =SUM(D11:D26) -> 2217400 | E27: =SUM(E11:E26) -> 900 | F27: =SUM(C27:E27) -> 3786360.7 | G27: =SUM(B27:E27) -> 3943888.4
